requests_default/__init__.py
requests_default/requests_default.py
requests_default-0.1.1.dist-info/LICENSE
requests_default-0.1.1.dist-info/WHEEL
requests_default-0.1.1.dist-info/METADATA
requests_default-0.1.1.dist-info/RECORD
